wtforms_django/__init__.py
wtforms_django/fields.py
wtforms_django/i18n.py
wtforms_django/orm.py
WTForms_Django-0.1.dist-info/DESCRIPTION.rst
WTForms_Django-0.1.dist-info/METADATA
WTForms_Django-0.1.dist-info/pydist.json
WTForms_Django-0.1.dist-info/RECORD
WTForms_Django-0.1.dist-info/top_level.txt
WTForms_Django-0.1.dist-info/WHEEL
