Metadata-Version: 2.0
Name: WTForms-Django
Version: 0.1
Summary: Django tools for WTForms
Home-page: http://github.com/wtforms/wtforms-appengine/
Author: Thomas Johansson, James Crasta
Author-email: wtforms@simplecodes.com
License: BSD
Platform: UNKNOWN
Classifier: Development Status :: 5 - Production/Stable
Classifier: Environment :: Web Environment
Classifier: Intended Audience :: Developers
Classifier: License :: OSI Approved :: BSD License
Classifier: Operating System :: OS Independent
Classifier: Programming Language :: Python
Classifier: Programming Language :: Python :: 2.6
Classifier: Programming Language :: Python :: 2.7
Classifier: Programming Language :: Python :: 3
Classifier: Programming Language :: Python :: 3.3
Classifier: Topic :: Internet :: WWW/HTTP :: Dynamic Content
Classifier: Topic :: Software Development :: Libraries :: Python Modules
Requires-Dist: WTForms (>=1.0.5)
Requires-Dist: Django (>=1.3)
